[
  {
    "id": 1,
    "firstname": "Rohan",
    "lastname": "Agarwal",
    "dob": "2006-12-31T18:30:00.000Z",
    "email": "rohan.agarwal7568@gmail.com",
    "mobile": "7976721448",
    "insurance": "insurance",
    "questions": [
      "yes",
      "yes",
      "yes",
      "yes",
      "yes"
    ],
    "gender": "Male",
    "marital_status": "M",
    "emergency_contact_name": "Rahul ",
    "emergency_contact_number": "7976721448",
    "address": "Sen Colony",
    "suggestion": "",
    "captchaVerification": "jwxi3q",
    "patientId": 144,
    "isRegistered": true,
    "created_at": "2025-01-13T14:19:32.706Z",
    "updated_at": "2025-01-13T14:20:56.507Z",
    "whitelist": "eyJhbGciOiJIUzI1NiIsInR5cCI6IkpXVCJ9.eyJlbWFpbCI6InJvaGFuLmFnYXJ3YWw3NTY4QGdtYWlsLmNvbSIsImlhdCI6MTczNjc3Nzk3MiwiZXhwIjoxNzM2ODY0MzcyfQ.l5LuvpTVxGdkm2S8YNYlunj79hhx3n1graFXG3UbDXw",
    "password": "3de73fccbecd70f12002bd48c9e1e62e:cf19272816e4febe291b",
    "verifiedToken": "eyJhbGciOiJIUzI1NiIsInR5cCI6IkpXVCJ9.eyJlbWFpbCI6InJvaGFuLmFnYXJ3YWw3NTY4QGdtYWlsLmNvbSIsImlhdCI6MTczNjc3Nzk3MiwiZXhwIjoxNzM2ODY0MzcyfQ.l5LuvpTVxGdkm2S8YNYlunj79hhx3n1graFXG3UbDXw"
  },
  {
    "id": 2,
    "firstname": "Rahul",
    "lastname": "Aggarwal",
    "dob": "2000-01-28T18:30:00.000Z",
    "email": "rahul93149@gmail.com",
    "mobile": "7976721448",
    "insurance": "aaaa",
    "questions": [
      "yes",
      "yes",
      "yes",
      "yes",
      "yes"
    ],
    "gender": "Male",
    "marital_status": "S",
    "emergency_contact_name": "Rahul ",
    "emergency_contact_number": "7976721448",
    "address": "A3",
    "suggestion": "",
    "captchaVerification": "2I4wn0",
    "terms": true,
    "patientId": 145,
    "isRegistered": "false",
    "created_at": "2025-01-13T16:49:34.815Z",
    "updated_at": "2025-01-13T16:49:34.816Z",
    "whitelist": "eyJhbGciOiJIUzI1NiIsInR5cCI6IkpXVCJ9.eyJlbWFpbCI6InJhaHVsOTMxNDlAZ21haWwuY29tIiwiaWF0IjoxNzM2Nzg2OTc0LCJleHAiOjE3MzY4NzMzNzR9.Gy2hewTF1lPE7LQZJGD6cBPn8o1rrfDHQhAQ-io3W7w"
  },
  {
    "id": 3,
    "firstname": "Rohan",
    "lastname": "Agarwal",
    "dob": "2007-01-02T18:30:00.000Z",
    "email": "rohanagarwal1802@gmail.com",
    "mobile": "7976721448",
    "insurance": "aaa",
    "questions": [
      "yes",
      "yes",
      "yes",
      "yes",
      "yes"
    ],
    "gender": "Male",
    "marital_status": "S",
    "emergency_contact_name": "aaa",
    "emergency_contact_number": "7976721448",
    "address": "aaa",
    "suggestion": "a",
    "captchaVerification": "ipzy8n",
    "terms": true,
    "patientId": 146,
    "isRegistered": true,
    "created_at": "2025-01-13T16:51:53.930Z",
    "updated_at": "2025-01-13T17:06:40.953Z",
    "whitelist": "eyJhbGciOiJIUzI1NiIsInR5cCI6IkpXVCJ9.eyJlbWFpbCI6InJvaGFuYWdhcndhbDE4MDJAZ21haWwuY29tIiwiaWF0IjoxNzM2Nzg3MTEzLCJleHAiOjE3MzY4NzM1MTN9.22WfqdLY47SdbFn76aClRpiD7GFwb9Dgisqnz0OOHao",
    "password": "c4fff1a9f96d28c8601640f0cdea2cc2:8af4d30f7698ff4ce6de",
    "verifiedToken": "eyJhbGciOiJIUzI1NiIsInR5cCI6IkpXVCJ9.eyJlbWFpbCI6InJvaGFuYWdhcndhbDE4MDJAZ21haWwuY29tIiwiaWF0IjoxNzM2Nzg3MTEzLCJleHAiOjE3MzY4NzM1MTN9.22WfqdLY47SdbFn76aClRpiD7GFwb9Dgisqnz0OOHao"
  }
]